alogging/__init__.py
alogging/backend.py
alogging/handlers.py
alogging/helpers.py
alogging/logger.py
py_extensions_alogging-0.1.1.dist-info/METADATA
py_extensions_alogging-0.1.1.dist-info/WHEEL
py_extensions_alogging-0.1.1.dist-info/entry_points.txt
py_extensions_alogging-0.1.1.dist-info/RECORD
