Metadata-Version: 2.1
Name: py-extensions-alogging
Version: 0.1.1
Summary: Async Logging for Python
Home-page: https://github.com/py-extensions/alogging
License: MIT
Keywords: logging,async,asyncio,python,py-extensions
Author: Yury Sokov
Author-email: me@yurzs.dev
Requires-Python: >=3.9,<4.0
Classifier: License :: OSI Approved :: MIT License
Classifier: Programming Language :: Python :: 3
Classifier: Programming Language :: Python :: 3.9
Classifier: Programming Language :: Python :: 3.10
Classifier: Programming Language :: Python :: 3.11
Classifier: Programming Language :: Python :: 3.12
Project-URL: Repository, https://github.com/py-extensions/alogging
